multinterp/__init__.py
multinterp/_version.py
multinterp/_version.pyi
multinterp/grids.py
multinterp/py.typed
multinterp/utilities.py
multinterp/backend/LBFGS.py
multinterp/backend/__init__.py
multinterp/backend/_cupy.py
multinterp/backend/_jax.py
multinterp/backend/_numba.py
multinterp/backend/_scipy.py
multinterp/backend/_torch.py
multinterp/curvilinear/__init__.py
multinterp/curvilinear/_scikit_image.py
multinterp/curvilinear/_scikit_learn.py
multinterp/curvilinear/_warped.py
multinterp/rectilinear/_multi.py
multinterp/rectilinear/_utils.py
multinterp/unstructured/__init__.py
multinterp/unstructured/_gpytorch.py
multinterp/unstructured/_scikit_learn.py
multinterp/unstructured/_scipy.py
multinterp-0.3.2.dist-info/METADATA
multinterp-0.3.2.dist-info/WHEEL
multinterp-0.3.2.dist-info/licenses/LICENSE
multinterp-0.3.2.dist-info/RECORD
