Metadata-Version: 2.3
Name: multinterp
Version: 0.3.2
Summary: Multivariate Interpolation.
Project-URL: Homepage, https://github.com/alanlujan91/multinterp
Project-URL: Bug Tracker, https://github.com/alanlujan91/multinterp/issues
Project-URL: Discussions, https://github.com/alanlujan91/multinterp/discussions
Project-URL: Changelog, https://github.com/alanlujan91/multinterp/releases
Author-email: Alan Lujan <alanlujan91@gmail.com>
Maintainer: All the contributors.
License: Copyright 2024 Alan Lujan
License-File: LICENSE
Keywords: interpolation,multidimensional,multivariate
Classifier: Development Status :: 1 - Planning
Classifier: Environment :: GPU
Classifier: Intended Audience :: Developers
Classifier: Intended Audience :: Science/Research
Classifier: License :: OSI Approved :: MIT License
Classifier: Natural Language :: English
Classifier: Operating System :: OS Independent
Classifier: Programming Language :: Python
Classifier: Programming Language :: Python :: 3
Classifier: Programming Language :: Python :: 3 :: Only
Classifier: Programming Language :: Python :: 3.8
Classifier: Programming Language :: Python :: 3.9
Classifier: Programming Language :: Python :: 3.10
Classifier: Programming Language :: Python :: 3.11
Classifier: Programming Language :: Python :: 3.12
Classifier: Topic :: Scientific/Engineering
Classifier: Topic :: Scientific/Engineering :: Mathematics
Classifier: Typing :: Typed
Requires-Python: >=3.8
Requires-Dist: numpy
Requires-Dist: scikit-image
Requires-Dist: scikit-learn
Requires-Dist: scipy
Provides-Extra: cupy
Requires-Dist: cupy; extra == 'cupy'
Provides-Extra: dev
Requires-Dist: pytest-cov>=3; extra == 'dev'
Requires-Dist: pytest>=6; extra == 'dev'
Provides-Extra: docs
Requires-Dist: furo>=2023.08.17; extra == 'docs'
Requires-Dist: myst-parser>=0.13; extra == 'docs'
Requires-Dist: sphinx-autodoc-typehints; extra == 'docs'
Requires-Dist: sphinx-copybutton; extra == 'docs'
Requires-Dist: sphinx>=7.0; extra == 'docs'
Provides-Extra: jax
Requires-Dist: jax; extra == 'jax'
Requires-Dist: jaxlib; extra == 'jax'
Provides-Extra: numba
Requires-Dist: numba; extra == 'numba'
Provides-Extra: test
Requires-Dist: pytest-cov>=3; extra == 'test'
Requires-Dist: pytest>=6; extra == 'test'
Provides-Extra: torch
Requires-Dist: gpytorch; extra == 'torch'
Requires-Dist: pytorch; extra == 'torch'
